Workbook

Sheet Scope Checklist
A1: COMPLETE RENOVATION - PENDING ITEMS + COST TRACKER | H1: RACI | I1: Responsible | J1: Accountable | K1: Consulted | L1: Informed
A2: Project: | B2: Jupiter | E2: Baseline start: | F2: ='Schedule Logic'!C3 -> 46300
A3: Updated: July 2, 2026 - costs per Project Status & Cost Summary PDF
A4: Schedule proposal Sep 24, 2026 (session 2026-ACTA-JUPITER-01): dates in F-H are driven by 'Schedule Logic'. N1-N12 = activities added from the 21-Sep session.
A5: # | B5: Category | C5: Area | D5: Scope Item | E5: Status | F5: Start Day | G5: End Day | H5: Effort (Hours) | I5: Progress (%) | J5: Exec Order | K5: Owner | L5: Total Cost | M5: Balance Due | N5: Vendor / Sub | O5: Notes
A6: PRE-CONSTRUCTION
A7: 1 | B7: Pre-Construction | C7: General | D7: Architecture & Engineering design and proposal | E7: Pending | F7: ='Schedule Logic'!G9 -> 46307 | G7: ='Schedule Logic'!H9 -> 46325 | H7: ='Schedule Logic'!I9 -> 60 | I7: 0 | J7: - | O7: Plan Drafting, caculations, Architectural Plan, Electrical Plan, Plumbing Plan, Mechanical Plan,
A8: 2 | B8: Pre-Construction | C8: General | D8: Determine specification sheets (Render) | E8: Pending | F8: ='Schedule Logic'!G7 -> 46300 | G8: ='Schedule Logic'!H7 -> 46311 | H8: ='Schedule Logic'!I7 -> 40 | I8: 0 | O8: It defines the type of finish and material to be used
A9: 3 | B9: Pre-Construction | C9: General | D9: Architecture & Engineering Approval | E9: Pending | F9: ='Schedule Logic'!G10 -> 46328 | G9: ='Schedule Logic'!H10 -> 46332 | H9: ='Schedule Logic'!I10 -> 6 | I9: 0
B10: Pre-Construction | C10: General | D10: Select provides and assign budget | E10: Pending | F10: ='Schedule Logic'!G11 -> 46314 | G10: ='Schedule Logic'!H11 -> 46332 | H10: ='Schedule Logic'!I11 -> 24 | I10: 0 | O10: PO Created for each case, set the date for procurement Determine material supplier & Labor provider
A11: 4 | B11: Pre-Construction | C11: General | D11: Property boundary survey | E11: Complete | I11: 1
A12: 5 | B12: Pre-Construction | C12: General | D12: HOA / ARB approval - Garage Door | E12: Pending | F12: ='Schedule Logic'!G12 -> 46314 | G12: ='Schedule Logic'!H12 -> 46332 | H12: ='Schedule Logic'!I12 -> 3 | I12: 0 | J12: -
A13: 6 | B13: Pre-Construction | C13: General | D13: HOA / ARB approval - exterior paint | E13: Pending | F13: ='Schedule Logic'!G13 -> 46314 | G13: ='Schedule Logic'!H13 -> 46332 | H13: ='Schedule Logic'!I13 -> 3 | I13: 0 | J13: -
A14: 7 | B14: Pre-Construction | C14: General | D14: HOA / ARB approval - driveway | E14: Pending | F14: ='Schedule Logic'!G14 -> 46314 | G14: ='Schedule Logic'!H14 -> 46332 | H14: ='Schedule Logic'!I14 -> 3 | I14: 0 | J14: -
A15: 8 | B15: Pre-Construction | C15: General | D15: HOA / ARB approval - Landscaping | E15: Pending | F15: ='Schedule Logic'!G15 -> 46314 | G15: ='Schedule Logic'!H15 -> 46332 | H15: ='Schedule Logic'!I15 -> 3 | I15: 0
A16: 9 | B16: Pre-Construction | C16: General | D16: Obtain access to Online Portal | E16: Pending | F16: ='Schedule Logic'!G8 -> 46300 | G16: ='Schedule Logic'!H8 -> 46301 | H16: ='Schedule Logic'!I8 -> 2 | I16: 0 | O16: Portal depends on the city: Town of Jupiter
A17: 10 | B17: Pre-Construction | C17: General | D17: Certificate of insurance per trade per jurisdiction | E17: Pending | F17: ='Schedule Logic'!G16 -> 46321 | G17: ='Schedule Logic'!H16 -> 46332 | H17: ='Schedule Logic'!I16 -> 6 | I17: 0 | O17: To: County City HOA
A18: 11 | B18: Pre-Construction | C18: General | D18: Workers compensation per trade | E18: Pending | F18: ='Schedule Logic'!G17 -> 46321 | G18: ='Schedule Logic'!H17 -> 46332 | H18: ='Schedule Logic'!I17 -> 4 | I18: 0 | O18: Ongoing document
A19: 12 | B19: Pre-Construction | C19: General | D19: DBPR license per trade | E19: Pending | F19: ='Schedule Logic'!G18 -> 46321 | G19: ='Schedule Logic'!H18 -> 46332 | H19: ='Schedule Logic'!I18 -> 3 | I19: 0
A20: 13 | B20: Pre-Construction | C20: General | D20: Notice of Commencement (NOC) | E20: Pending | F20: ='Schedule Logic'!G20 -> 46339 | G20: ='Schedule Logic'!H20 -> 46343 | H20: ='Schedule Logic'!I20 -> 4 | I20: 0 | J20: W1-01 | K20: A | O20: Based on Martin County: Obtain the correct file Fill-out Notarize Record
A21: 14 | B21: Pre-Construction | C21: Permits | D21: Permits package submittal | E21: Pending | F21: ='Schedule Logic'!G19 -> 46335 | G21: ='Schedule Logic'!H19 -> 46338 | H21: ='Schedule Logic'!I19 -> 12 | I21: 0 | J21: - | K21: - | O21: Permit Application per trade https://www.jupiter.fl.us/98/Permit-Package-Submittal
A22: 15 | B22: Pre-Construction | C22: Permits | D22: GC master permit - Residential alterations and additions | E22: Pending | F22: ='Schedule Logic'!G21 -> 46339 | G22: ='Schedule Logic'!H21 -> 46370 | H22: ='Schedule Logic'!I21 -> 8 | I22: 0 | O22: Residential-AlterationsAdditions
A23: 16 | B23: Pre-Construction | C23: Permits | D23: Mechanical permit | E23: Pending | F23: ='Schedule Logic'!G22 -> 46346 | G23: ='Schedule Logic'!H22 -> 46370 | H23: ='Schedule Logic'!I22 -> 4 | I23: 0 | J23: W1-04 | K23: A | O23: Mechanical
A24: 17 | B24: Pre-Construction | C24: Permits | D24: Electrical permit | E24: Pending | F24: ='Schedule Logic'!G23 -> 46346 | G24: ='Schedule Logic'!H23 -> 46370 | H24: ='Schedule Logic'!I23 -> 4 | I24: 0 | J24: W1-03 | K24: A | O24: Please submit/upload plans in PDF format
A25: 18 | B25: Pre-Construction | C25: Permits | D25: Plumbing permit | E25: Pending | F25: ='Schedule Logic'!G24 -> 46346 | G25: ='Schedule Logic'!H24 -> 46370 | H25: ='Schedule Logic'!I24 -> 4 | I25: 0 | J25: W1-02 | K25: A | O25: Plumbing
A26: 19 | B26: Pre-Construction | C26: Permits | D26: Fence permit | E26: Pending | F26: ='Schedule Logic'!G25 -> 46339 | G26: ='Schedule Logic'!H25 -> 46356 | H26: ='Schedule Logic'!I25 -> 3 | I26: 0 | J26: W1-05 | K26: A + V | O26: Fences
A27: 20 | B27: Pre-Construction | C27: Permits | D27: Driveway permit | E27: Pending | F27: ='Schedule Logic'!G26 -> 46339 | G27: ='Schedule Logic'!H26 -> 46356 | H27: ='Schedule Logic'!I26 -> 3 | I27: 0 | J27: W1-06 | K27: A + V | O27: Concrete, Patios, Decks, Slabs, Pavers Dec21.docx
A28: 21 | B28: Pre-Construction | C28: Permits | D28: Gazebo permit | E28: Pending | F28: ='Schedule Logic'!G27 -> 46339 | G28: ='Schedule Logic'!H27 -> 46356 | H28: ='Schedule Logic'!I27 -> 3 | I28: 0 | O28: Gazebo-Dec1.docx
A29: 22 | B29: Pre-Construction | C29: Permits | D29: Garage-door permit | E29: Pending | F29: ='Schedule Logic'!G28 -> 46339 | G29: ='Schedule Logic'!H28 -> 46356 | H29: ='Schedule Logic'!I28 -> 3 | I29: 0 | O29: Garage-Door-Replacement
A30: 23 | B30: Pre-Construction | C30: General | D30: Demolition & Waste Management | E30: In Progress | F30: ='Schedule Logic'!G29 -> 46300 | G30: ='Schedule Logic'!H29 -> 46413 | H30: ='Schedule Logic'!I29 -> 10 | I30: 0.9 | J30: Ongoing | O30: Dumpster / waste disposal
A31: 24 | B31: Pre-Construction | C31: General | D31: Utilities | E31: In Progress | F31: ='Schedule Logic'!G30 -> 46300 | G31: ='Schedule Logic'!H30 -> Ongoing | H31: ='Schedule Logic'!I30 -> 2 | J31: - | O31: All utilities on autopay, up to date
A32: INTERIOR - DEMO/STRUCTURE
A33: 52 | B33: Interior - Demo/Structure | C33: General | D33: Interior demolition | E33: Complete | I33: 1 | J33: - | O33: Wall partitions, flooring, baseborads, doors, trim, bathrooms and kitchen
A34: 54 | B34: Interior - Demo/Structure | C34: General | D34: Drywall repair / install + skim coat. Initial phase complete | E34: Complete | I34: 1 | J34: W1-08 | K34: V
A35: N1 | B35: Interior - Demo/Structure | C35: General | D35: Site protection + inventory (windows, railings, outlets, switches, smoke detectors) | E35: Pending | F35: ='Schedule Logic'!G32 -> 46300 | G35: ='Schedule Logic'!H32 -> 46301 | H35: ='Schedule Logic'!I32 -> 12 | I35: 0 | J35: - | K35: A + V | O35: Added from 21-Sep session [16:10]-[17:08]: tape/plastic on windows + railings; inventory and cover outlets, switches, smoke detectors before any new trade enters (lesson: tile crew cement on windows/railings); seal AC returns/registers, air handler off or filtered during dusty work
A36: N2 | B36: Interior - Demo/Structure | C36: Structure | D36: Structural engineering review - removed interior walls / truss bearing | E36: Pending | F36: ='Schedule Logic'!G33 -> 46300 | G36: ='Schedule Logic'!H33 -> 46309 | H36: ='Schedule Logic'!I33 -> 8 | I36: 0 | J36: - | K36: A / Sub | O36: Added from 21-Sep session [14:41]-[15:36]: engineer verifies roof trusses bear on perimeter walls; signed + sealed letter feeds A&E plans and framing permit
A37: 56 | B37: Interior - Demo/Structure | C37: General | D37: Popcorn ceiling removal - flat finish & skin coat | E37: Pending | F37: ='Schedule Logic'!G34 -> 46302 | G37: ='Schedule Logic'!H34 -> 46311 | H37: ='Schedule Logic'!I34 -> 64 | I37: 0 | J37: - | K37: Sub | O37: All applicable areas included garage. Asbestos test on texture BEFORE scraping (lab 2-3 days); scrape + first flat coat now, final skim after MEP rough-in (recessed light cuts)
A38: 53 | B38: Interior - Demo/Structure | C38: General | D38: Framing repairs / new partitions | E38: Pending | F38: ='Schedule Logic'!G35 -> 46371 | G38: ='Schedule Logic'!H35 -> 46377 | H38: ='Schedule Logic'!I35 -> 60 | I38: 0 | J38: - | K38: V | O38: Master Bathroom walls, Master closet walls, kitchen island. Requires engineer letter (N2) + GC master permit issued
A39: N3 | B39: Interior - Demo/Structure | C39: Structure | D39: Slab trench patch after underground plumbing (baths/kitchen) + slab inspection | E39: Pending | F39: ='Schedule Logic'!G36 -> 46377 | G39: ='Schedule Logic'!H36 -> 46379 | H39: ='Schedule Logic'!I36 -> 16 | I39: 0 | J39: - | K39: V | O39: Added from 21-Sep session [52:36]-[53:16]: underground plumbing inspection (P-trap, slope) must PASS before slab is closed; then slab/structure + plumbing inspections run together
A40: 57 | B40: Interior - Demo/Structure | C40: General | D40: Concrete slab repair + tile infill under AC unit | E40: Pending | F40: ='Schedule Logic'!G37 -> 46371 | G40: ='Schedule Logic'!H37 -> 46372 | H40: ='Schedule Logic'!I37 -> 12 | I40: 0 | J40: W1-09 | K40: V | O40: Slab below equipment requires repair; cost in HVAC maintenance line; small demo required; V: demo tile in closet, install new tile
A41: N4 | B41: Interior - Demo/Structure | C41: Inspections | D41: Framing + MEP rough-in inspections (pre-cover milestone) | E41: Pending | F41: ='Schedule Logic'!G38 -> 46387 | G41: ='Schedule Logic'!H38 -> 46394 | H41: ='Schedule Logic'!I38 -> 8 | I41: 0 | J41: - | K41: A | O41: Added from 21-Sep session [35:22]-[40:28]: schedule via MGO; inspector usually next day; sealed large-format plans on site for inspector comments. Gate for closing walls (drywall)
B42: Interior - Demo/Structure | C42: General | D42: Drywall repair / install & finish. 2nd phase | E42: Pending | F42: ='Schedule Logic'!G39 -> 46395 | G42: ='Schedule Logic'!H39 -> 46401 | H42: ='Schedule Logic'!I39 -> 80 | I42: 0 | J42: W2-19 | K42: V | O42: Corner bead finish + paint at windows/doors. Hang + tape new partitions only after framing/MEP rough-in inspections PASS (N4)
B43: Interior - Demo/Structure | C43: General | D43: Drywall repair / install & finish. Final phase | E43: Pending | F43: ='Schedule Logic'!G40 -> 46402 | G43: ='Schedule Logic'!H40 -> 46408 | H43: ='Schedule Logic'!I40 -> 60 | I43: 0 | J43: W1-08 | K43: V | O43: Final sand + popcorn-ceiling final skim; surfaces ready for primer
A44: N5 | B44: Interior - Demo/Structure | C44: General | D44: Surface prep - primer on walls + ceilings | E44: Pending | F44: ='Schedule Logic'!G41 -> 46409 | G44: ='Schedule Logic'!H41 -> 46413 | H44: ='Schedule Logic'!I41 -> 40 | I44: 0 | J44: - | K44: H | O44: Added from 21-Sep session [18:17]-[19:44]: first coat = primer (wall/ceiling specific) before wet trades; improves adhesion, fewer paint coats
B45: Interior - Demo/Structure | C45: General | D45: Attic insulation | E45: Not Needed | J45: -
A46: INTERIOR - ELECTRICAL
A47: 59 | B47: Interior - Electrical | C47: Contract | D47: Electrical contract - overall | E47: In Progress | F47: ='Schedule Logic'!G55 -> 46300 | G47: ='Schedule Logic'!H55 -> 46448 | H47: ='Schedule Logic'!I55 -> - | J47: W2-02 | K47: Sub | L47: 14000 | M47: 7000 | O47: $7,000 paid / $7,000 balance; final inspection pending; remaining: light fixtures + fans, all outlets + switches, kitchen chandelier, exterior floodlight, kitchen LED lighting, bath exhaust fans, bathtub electrical connection, LED mirror install
A48: N6 | B48: Interior - Electrical | C48: Whole house | D48: Make-safe exposed wiring from demolition (cap, label, temp lighting) | E48: Pending | F48: ='Schedule Logic'!G45 -> 46300 | G48: ='Schedule Logic'!H45 -> 46300 | H48: ='Schedule Logic'!I45 -> 6 | I48: 0 | J48: - | K48: Sub | O48: Added from 21-Sep session [14:34]-[14:41]: loose conductors left where partitions were removed; cap/label live circuits before trades return
A49: 60 | B49: Interior - Electrical | C49: Whole house | D49: Electrical panel change out | E49: In Progress | F49: ='Schedule Logic'!G46 -> 46371 | G49: ='Schedule Logic'!H46 -> 46372 | H49: ='Schedule Logic'!I46 -> 12 | J49: W1-10 | K49: A + V | O49: Permit pending; Panel already installed; V: add labels to cover, identify amperage + service; A: schedule + pass inspection
A50: N7 | B50: Interior - Electrical | C50: Whole house | D50: Electrical rough-in - relocated boxes, new kitchen/bath circuits | E50: Pending | F50: ='Schedule Logic'!G47 -> 46378 | G50: ='Schedule Logic'!H47 -> 46386 | H50: ='Schedule Logic'!I47 -> 60 | I50: 0 | J50: - | K50: Sub | O50: Added from 21-Sep session [12:07]-[12:38]: open-concept kitchen + removed walls = relocate boxes/switch legs; dedicated circuits fridge, oven, DW, disposal, hood; bath fans, tub, LED niches. Inspected in N4
A51: 61 | B51: Interior - Electrical | C51: Whole house | D51: Outlets, switches, GFCI/AFCI | E51: Pending | F51: ='Schedule Logic'!G48 -> 46443 | G51: ='Schedule Logic'!H48 -> 46447 | H51: ='Schedule Logic'!I48 -> 24 | I51: 0 | J51: W2-02 | K51: Sub | O51: All pending install, including switches; in electrical contract; Include dedicated outlets for refrigerator + oven; Purchase W1 (A purchase session)
A52: 62 | B52: Interior - Electrical | C52: Whole house | D52: Recessed lighting (LED) | E52: In Progress | F52: ='Schedule Logic'!G49 -> 46443 | G52: ='Schedule Logic'!H49 -> 46444 | H52: ='Schedule Logic'!I49 -> 12 | J52: W2-02 | K52: Sub | O52: All installed and working except one recessed light in patio area
A53: 63 | B53: Interior - Electrical | C53: Whole house | D53: Ceiling fans | E53: Pending | F53: ='Schedule Logic'!G50 -> 46444 | G53: ='Schedule Logic'!H50 -> 46447 | H53: ='Schedule Logic'!I50 -> 12 | I53: 0 | J53: W2-02 | K53: Sub | O53: Purchased (patio, master, bed 2, bed 3, living); awaiting install; in electrical contract
A54: 64 | B54: Interior - Electrical | C54: Dining | D54: Dining fixture (kitchen chandelier) | E54: Pending | F54: ='Schedule Logic'!G51 -> 46447 | G54: ='Schedule Logic'!H51 -> 46447 | H54: ='Schedule Logic'!I51 -> 3 | I54: 0 | J54: W2-02 | K54: Sub | O54: Fixture on hand; reposition electrical box pending; install in electrical contract
A55: 65 | B55: Interior - Electrical | C55: Bathrooms | D55: LED mirrors - install | E55: Pending | F55: ='Schedule Logic'!G52 -> 46448 | G55: ='Schedule Logic'!H52 -> 46448 | H55: ='Schedule Logic'!I52 -> 4 | I55: 0 | J55: W3-04 | K55: V | O55: In electrical contract remaining work; Purchase in W1 session (A)
A56: 66 | B56: Interior - Electrical | C56: Whole house | D56: Smoke / CO detectors - replace all | E56: Pending | F56: ='Schedule Logic'!G53 -> 46448 | G56: ='Schedule Logic'!H53 -> 46448 | H56: ='Schedule Logic'!I53 -> 4 | I56: 0 | J56: W1-14 | K56: V > A | O56: Count pending; purchase pending; V: count detectors; A: purchase after count; existing detectors covered during protection (N1) - replace with interconnected units at trim
A57: 67 | B57: Interior - Electrical | C57: Whole house | D57: Doorbell / smart doorbell | E57: Pending | F57: ='Schedule Logic'!G54 -> 46448 | G57: ='Schedule Logic'!H54 -> 46448 | H57: ='Schedule Logic'!I54 -> 2 | I57: 0 | J57: W2-02 | K57: Sub
A58: INTERIOR - PLUMBING
A59: 68 | B59: Interior - Plumbing | C59: Whole house | D59: Plumbing redirects (in lieu of full repipe) | E59: Complete | I59: 1 | J59: - | O59: Lines redirected for new shower valves, new toilet position, new kitchen faucet + dishwasher locations; new fridge water line overhead in blue PEX
A60: N8 | B60: Interior - Plumbing | C60: Whole house | D60: Underground DWV rough-in (baths/kitchen) incl. P-traps + underground inspection PASS | E60: Pending | F60: ='Schedule Logic'!G57 -> 46371 | G60: ='Schedule Logic'!H57 -> 46374 | H60: ='Schedule Logic'!I57 -> 32 | I60: 0 | J60: - | K60: V | O60: Added from 21-Sep session [50:25]-[52:36]: a straight pipe without U/P-trap caused sewer gas and a finished shower had to be demolished. Camera-scope existing drains; do NOT close slab until inspector passes
A61: N9 | B61: Interior - Plumbing | C61: Whole house | D61: Water supply rough-in / top-out (shower valves, toilets, kitchen, fridge line) + pressure test | E61: Pending | F61: ='Schedule Logic'!G58 -> 46384 | G61: ='Schedule Logic'!H58 -> 46386 | H61: ='Schedule Logic'!I58 -> 24 | I61: 0 | J61: - | K61: V | O61: Added from 21-Sep session [53:00]-[53:16]: plumbing inspector checks open penetrations + blocking for liner; inspected in N4
A62: 71 | B62: Interior - Plumbing | C62: Whole house | D62: Plumbing inventory check - supply lines, drainage, P-traps | E62: Pending | F62: ='Schedule Logic'!G59 -> 46387 | G62: ='Schedule Logic'!H59 -> 46391 | H62: ='Schedule Logic'!I59 -> 6 | I62: 0 | J62: W2-03 | K62: V | O62: Confirm inventory for all: kitchen faucet, bathroom faucets, toilets; build list (P-traps etc.); purchase gaps
A63: 69 | B63: Interior - Plumbing | C63: Contract | D63: Final plumbing completion labor | E63: Pending | F63: ='Schedule Logic'!G60 -> 46443 | G63: ='Schedule Logic'!H60 -> 46447 | H63: ='Schedule Logic'!I60 -> 24 | I63: 0 | J63: W2-03 | K63: V | M63: 1500 | N63: Victor | O63: ~3 days labor at Victor's daily rate; final inspection pending; trim-out after cabinets, tops + tile (PROVISIONAL anchor in Schedule Logic)
A64: 72 | B64: Interior - Plumbing | C64: Whole house | D64: Angle stops and supply lines throughout | E64: Pending | F64: ='Schedule Logic'!G61 -> 46443 | G64: ='Schedule Logic'!H61 -> 46444 | H64: ='Schedule Logic'!I61 -> 8 | I64: 0 | J64: W2-03 | K64: V
A65: 70 | B65: Interior - Plumbing | C65: Whole house | D65: Water heater | E65: Not Needed | J65: - | O65: Working condition - keep
A66: INTERIOR - HVAC
A67: 73 | B67: Interior - HVAC | C67: Whole house | D67: AC unit replacement | E67: Not Needed | J67: - | O67: Keeping existing unit; permit + inspection to cure open violation
A68: 74 | B68: Interior - HVAC | C68: Contract | D68: HVAC maintenance + concrete slab repair | E68: Pending | F68: ='Schedule Logic'!G69 -> 46371 | G68: ='Schedule Logic'!H69 -> 46415 | H68: ='Schedule Logic'!I69 -> - | I68: 0 | J68: W1-09 | K68: A / Sub | L68: 2100 | M68: 2000 | O68: $1,000-$2,100 range; final cost depends on slab repaired in-house vs fully replaced; permit + inspection required (quick turnaround); A: hire service company
A69: N10 | B69: Interior - HVAC | C69: Whole house | D69: Duct modifications - removed partitions, kitchen hood + bath exhaust ducting | E69: Pending | F69: ='Schedule Logic'!G63 -> 46378 | G69: ='Schedule Logic'!H63 -> 46384 | H69: ='Schedule Logic'!I63 -> 24 | I69: 0 | J69: - | K69: Sub | O69: Added from 21-Sep session [12:07]-[12:38] + [33:19]: walls removed for open concept may carry supply/return runs; hood + bath fan ducts (master coupling pending) go in before walls close. Mechanical rough inspected in N4
A70: 77 | B70: Interior - HVAC | C70: Whole house | D70: Ductwork inspection / repair / clean | E70: Pending | F70: ='Schedule Logic'!G64 -> 46414 | G70: ='Schedule Logic'!H64 -> 46415 | H70: ='Schedule Logic'!I64 -> 16 | I70: 0 | J70: W1-09 | K70: Sub | O70: Clean AFTER drywall sanding + primer (dust); returns/registers sealed and filters changed during dusty work
A71: 75 | B71: Interior - HVAC | C71: Whole house | D71: HVAC coil cleaning | E71: Pending | F71: ='Schedule Logic'!G65 -> 46414 | G71: ='Schedule Logic'!H65 -> 46414 | H71: ='Schedule Logic'!I65 -> 4 | I71: 0 | J71: W1-09 | K71: Sub | O71: Part of maintenance line
A72: 76 | B72: Interior - HVAC | C72: Whole house | D72: HVAC coolant refill service | E72: Pending | F72: ='Schedule Logic'!G66 -> 46414 | G72: ='Schedule Logic'!H66 -> 46414 | H72: ='Schedule Logic'!I66 -> 3 | I72: 0 | J72: W1-09 | K72: Sub | O72: Part of maintenance line
A73: 78 | B73: Interior - HVAC | C73: Whole house | D73: AC diffusers | E73: Pending | F73: ='Schedule Logic'!G67 -> 46443 | G73: ='Schedule Logic'!H67 -> 46443 | H73: ='Schedule Logic'!I67 -> 4 | I73: 0 | J73: W1-14 | K73: A | O73: Purchase + install pending; A: purchase diffusers
A74: 79 | B74: Interior - HVAC | C74: Whole house | D74: Thermostat | E74: Pending | F74: ='Schedule Logic'!G68 -> 46443 | G74: ='Schedule Logic'!H68 -> 46443 | H74: ='Schedule Logic'!I68 -> 2 | I74: 0 | J74: W1-14 | K74: V | O74: Return/exchange thermostat; install pending; V: pack thermostat + return via UPS
A75: KITCHEN
A76: N11 | B76: Kitchen | C76: Cabinetry | D76: Cabinet order - field-verify dimensions, PO + fabrication (3-4 wk) | E76: Pending | F76: ='Schedule Logic'!G71 -> 46378 | G76: ='Schedule Logic'!H71 -> 46408 | H76: ='Schedule Logic'!I71 -> 6 | I76: 0 | J76: - | K76: A | O76: Added from 21-Sep session [25:34]-[29:44]: ready-made / semi-custom cabinets, not fully custom; fabrication 3-4 wk (a half-size kitchen took 2 wk); only long-lead item [28:29]. Order after framing fixes dimensions + appliance specs (fridge 36 in width/depth, cooktop, hood); timed to land at primer end to defer cash [28:00]. Layout must first be approved by Jaime [13:21]
A77: 80 | B77: Kitchen | C77: Cabinetry | D77: Kitchen cabinets + bathroom vanities (combined contract) | E77: In Progress | F77: ='Schedule Logic'!G72 -> 46414 | G77: ='Schedule Logic'!H72 -> 46415 | H77: ='Schedule Logic'!I72 -> 16 | J77: W1-11 | K77: A + V | L77: 21750 | M77: 4875 | N77: Noel | O77: $16,875 paid / $4,875 balance; install by cabinet manufacturer, 1-2 days max; quality verification meeting Mon Jul 6, 11:00 AM; A & V both present at Noel appointment Mon Jul 6, 11 AM
A78: 81 | B78: Kitchen | C78: Countertops | D78: Stone countertops + backsplash (kitchen + baths) | E78: Pending | F78: ='Schedule Logic'!G73 -> 46416 | G78: ='Schedule Logic'!H73 -> 46427 | H78: ='Schedule Logic'!I73 -> 12 | I78: 0 | J78: W1-12 | K78: A / M | L78: 5925 | M78: 4500 | N78: Martin | O78: $3,950-$5,925 range at $50-$75/sq ft installed + fabricated; kitchen ~35 sq ft counter + ~25 sq ft backsplash; bath 2 ~8 sq ft; master ~11 sq ft; fabrication ~5 business days, install 1-2 days; CABINETS MUST BE FULLY INSTALLED BEFORE FIELD MEASUREMENTS; call Martin for quote; decide if kitchen differs from vanity tops + thresholds; A: request Martin appointment for same Monday Jul 6; Martin meeting Sat Jul 4 - V attends; M provides quote; A selects stone, purchases + makes down payment; M installs ~5 days after quote, subject to stone purchase + delivery availability
A79: 82 | B79: Kitchen | C79: Kitchen | D79: Kitchen sink - purchase | E79: Pending | F79: ='Schedule Logic'!G74 -> 46387 | G79: ='Schedule Logic'!H74 -> 46394 | H79: ='Schedule Logic'!I74 -> 3 | I79: 0 | J79: W1-13 | K79: A
A80: 83 | B80: Kitchen | C80: Kitchen | D80: Kitchen faucet | E80: Pending | F80: ='Schedule Logic'!G75 -> 46387 | G80: ='Schedule Logic'!H75 -> 46394 | H80: ='Schedule Logic'!I75 -> 2 | I80: 0 | J80: W1-13 | K80: V > A | O80: Purchase or verify purchase; V: verify faucet already purchased; if not, A purchases
A81: 84 | B81: Kitchen | C81: Kitchen | D81: Appliance package - purchase, transport, install | E81: Pending | F81: ='Schedule Logic'!G76 -> 46387 | G81: ='Schedule Logic'!H76 -> 46401 | H81: ='Schedule Logic'!I76 -> 16 | I81: 0 | J81: W1-14 | K81: A | L81: 9100 | M81: 9100 | O81: Samsung oven + microwave combo $3,700; cooktop $650; dishwasher $500; exhaust hood $500; garbage disposal $250; wine cooler $450; refrigerator $1,800; washer + dryer set $1,250; source via Facebook Marketplace where possible; delivery coordination + install scheduling pending; A: ongoing marketplace search; V: provide refrigerator depth (width confirmed 36 in); V: transport + install W1-W2 as items are acquired
A82: N12 | B82: Kitchen | C82: Kitchen | D82: Appliance install + hook-ups (oven, cooktop, DW, disposal, hood, fridge line) | E82: Pending | F82: ='Schedule Logic'!G77 -> 46448 | G82: ='Schedule Logic'!H77 -> 46449 | H82: ='Schedule Logic'!I77 -> 12 | I82: 0 | J82: - | K82: V | O82: Added: cooktop + sink templates go to the stone fabricator before fabrication; hook-ups need plumbing + electrical trim (dedicated oven/fridge outlets)
A83: 86 | B83: Kitchen | C83: Kitchen | D83: Under-cabinet lighting | E83: Pending | F83: ='Schedule Logic'!G78 -> 46443 | G83: ='Schedule Logic'!H78 -> 46443 | H83: ='Schedule Logic'!I78 -> 4 | I83: 0 | J83: W1-14 | K83: A | O83: Select transformer; select LED strip; puck light selection, count + purchase; kitchen LED in electrical contract; A: purchase LED lighting for cabinetry
A84: 85 | B84: Kitchen | C84: Kitchen | D84: Kitchen island | E84: Not Needed | J84: -
A85: BATH - MASTER
A86: 87 | B86: Bath - Master | C86: Vanity | D86: Vanity cabinetry - confirm quality | E86: Pending | J86: W1-11 | K86: A + V | N86: Noel | O86: In cabinet contract
A87: 88 | B87: Bath - Master | C87: Vanity | D87: Sink selection - double sinks | E87: Pending | J87: W1-13 | K87: A | O87: A purchases sinks
A88: 89 | B88: Bath - Master | C88: Vanity | D88: Vanity stone top - select (~11 sq ft) | E88: Pending | J88: W1-12 | K88: A | N88: Martin | O88: In stone contract line
A89: 90 | B89: Bath - Master | C89: Vanity | D89: Double faucets + double sinks - install | E89: Pending | J89: W3-02 | O89: Verify vanity height pending
A90: 91 | B90: Bath - Master | C90: Toilet | D90: Toilet install + new wax ring | E90: Pending | J90: W1-20 | K90: V | O90: New toilet position (drain relocated); New flange if necessary; verify supply line + drainage positioning; One row per bathroom (master + secondary)
A91: 92 | B91: Bath - Master | C91: Tub | D91: Tub install | E91: Pending | J91: W2-17 | O91: Bathtub electrical connection in electrical contract; Bathtub electrical connection ASAP in W1 - ready for inspection; set tub in W2 after inspections pass
A92: 93 | B92: Bath - Master | C92: Shower | D92: LED niche | E92: Pending | J92: W2-02 | K92: V | O92: ASAP - confirm inventory or place supply order
A93: 94 | B93: Bath - Master | C93: Shower | D93: Shower drains - select + purchase (BOTH baths) | E93: Pending | J93: W1-13 | K93: A | O93: Needed on hand before pan liner / tile sequence
A94: 95 | B94: Bath - Master | C94: Shower | D94: Shower prep - confirm metal frame distance + shower door frame support (BOTH baths) | E94: Pending | J94: W1-17 | K94: V | O94: Pre-liner check; do labor if needed; supports glass door install later
A95: 96 | B95: Bath - Master | C95: Shower | D95: Durock + waterproofing install | E95: Pending | J95: W1-18 | K95: V | O95: Shower sequence steps 3-4: Durock, then waterproofing - after pan liner inspection passes
A96: 97 | B96: Bath - Master | C96: Shower | D96: Pan liner install + inspection pass | E96: Pending | J96: W1-18 | K96: V | O96: Shower sequence step 2 (after step 1 framing); CANNOT start before permit issuance + plumbing/framing/slab inspections scheduled/passed
A97: 98 | B97: Bath - Master | C97: Shower | D97: Bathroom tile installation - labor (BOTH baths) | E97: Pending | J97: W2-01 | K97: Sub | M97: 3500 | O97: Complete bathroom tile install, both bathrooms; ~10 days total; Starts ONLY after framing, Durock, waterproofing + passed inspections (W1-18 sequence)
A98: 99 | B98: Bath - Master | C98: Shower | D98: Metal trim (edge profile) - verify availability | E98: Pending | J98: W1-14 | K98: V | O98: V: confirm metal trim color + count
A99: 100 | B99: Bath - Master | C99: Shower | D99: Threshold + bench top | E99: Pending | J99: W3-01 | K99: M | N99: Martin | O99: Coordinate stone with countertop selection
A100: 101 | B100: Bath - Master | C100: Shower | D100: Glass shower enclosure - MASTER | E100: Pending | J100: W3-03 | K100: G | L100: 3000 | M100: 3000 | N100: Gino | O100: $2,500-$3,000; fabrication ~4 days; install 1-2 days; measurements pending; Gino: quote + install MASTER
...

Sheet Schedule Logic
A1: SCHEDULE LOGIC - PRE-CONSTRUCTION, DEMO/STRUCTURE, ELECTRICAL, PLUMBING, HVAC, KITCHEN (proposed baseline)
A2: Working days Mon-Fri excluding holidays in column M. Edit only the yellow cells (baseline) and blue cells (lag, duration, effort); Start/End recalculate and feed Scope Checklist columns F-H.
A3: Baseline start | C3: 46300 | D3: Set by Andrés/Carlos on 24-Sep-2026 (leaves week of 28-Sep to close ARV / max-budget analysis)
A5: Scope row | B5: # | C5: Scope Item | D5: Predecessor (logic) | E5: Lag (wd) | F5: Duration (wd) | G5: Start | H5: End | I5: Effort (hrs) | J5: Owner | K5: Basis / Source | M5: Holidays
A6: PRE-CONSTRUCTION | M6: 46337 | N6: Veterans Day (city offices closed)
A7: 8 | B7: =IF('Scope Checklist'!A8="","-",'Scope Checklist'!A8) -> 2 | C7: ='Scope Checklist'!D8 -> Determine specification sheets (Render) | D7: Baseline start | E7: 0 | F7: 10 | G7: =$C$3 -> 46300 | H7: =WORKDAY(G7,F7-1,$M$6:$M$11) -> 46311 | I7: 40 | J7: A | K7: [10:25]-[11:15] one spec sheet (render) per room; must be validated by Jaime. Gate: max renovation budget from comps/ARV [43:15] | M7: 46352 | N7: Thanksgiving
A8: 16 | B8: =IF('Scope Checklist'!A16="","-",'Scope Checklist'!A16) -> 9 | C8: ='Scope Checklist'!D16 -> Obtain access to Online Portal | D8: Baseline start | E8: 0 | F8: 2 | G8: =$C$3 -> 46300 | H8: =WORKDAY(G8,F8-1,$M$6:$M$11) -> 46301 | I8: 2 | J8: A | K8: [31:37] MGO portal - select jurisdiction (Town of Jupiter); confirm county Palm Beach vs Martin [30:34] | M8: 46353 | N8: Day after Thanksgiving
A9: 7 | B9: =IF('Scope Checklist'!A7="","-",'Scope Checklist'!A7) -> 1 | C9: ='Scope Checklist'!D7 -> Architecture & Engineering design and proposal | D9: Starts 5 wd after spec sheets start (as-built first) | E9: 5 | F9: 15 | G9: =WORKDAY(G7,E9,$M$6:$M$11) -> 46307 | H9: =WORKDAY(G9,F9-1,$M$6:$M$11) -> 46325 | I9: 60 | J9: A / Sub | K9: [32:44]-[33:38] as-built + proposed plans incl. M/E/P; drafted in-house [38:25] - recommend delegating | M9: 46380 | N9: Christmas Eve
A10: 9 | B10: =IF('Scope Checklist'!A9="","-",'Scope Checklist'!A9) -> 3 | C10: ='Scope Checklist'!D9 -> Architecture & Engineering Approval | D10: After A&E design | E10: 0 | F10: 5 | G10: =WORKDAY(H9,1+E10,$M$6:$M$11) -> 46328 | H10: =WORKDAY(G10,F10-1,$M$6:$M$11) -> 46332 | I10: 6 | J10: A | K10: [39:37]-[39:48] engineer signs/seals before city submittal | M10: 46381 | N10: Christmas
A11: 10 | B11: =IF('Scope Checklist'!A10="","-",'Scope Checklist'!A10) -> - | C11: ='Scope Checklist'!D10 -> Select provides and assign budget | D11: After spec sheets | E11: 0 | F11: 15 | G11: =WORKDAY(H7,1+E11,$M$6:$M$11) -> 46314 | H11: =WORKDAY(G11,F11-1,$M$6:$M$11) -> 46332 | I11: 24 | J11: A | K11: [28:00]-[28:29] kitchen cabinets 3-4 wk fabrication = long-lead item; everything else available immediately | M11: 46388 | N11: New Year's Day
A12: 12 | B12: =IF('Scope Checklist'!A12="","-",'Scope Checklist'!A12) -> 5 | C12: ='Scope Checklist'!D12 -> HOA / ARB approval - Garage Door | D12: After spec sheets | E12: 0 | F12: 15 | G12: =WORKDAY(H7,1+E12,$M$6:$M$11) -> 46314 | H12: =WORKDAY(G12,F12-1,$M$6:$M$11) -> 46332 | I12: 3 | J12: A | K12: Assumption: ARB review ~3 weeks; confirm HOA meeting calendar
A13: 13 | B13: =IF('Scope Checklist'!A13="","-",'Scope Checklist'!A13) -> 6 | C13: ='Scope Checklist'!D13 -> HOA / ARB approval - exterior paint | D13: After spec sheets | E13: 0 | F13: 15 | G13: =WORKDAY(H7,1+E13,$M$6:$M$11) -> 46314 | H13: =WORKDAY(G13,F13-1,$M$6:$M$11) -> 46332 | I13: 3 | J13: A | K13: Assumption: submitted together with garage door package
A14: 14 | B14: =IF('Scope Checklist'!A14="","-",'Scope Checklist'!A14) -> 7 | C14: ='Scope Checklist'!D14 -> HOA / ARB approval - driveway | D14: After spec sheets | E14: 0 | F14: 15 | G14: =WORKDAY(H7,1+E14,$M$6:$M$11) -> 46314 | H14: =WORKDAY(G14,F14-1,$M$6:$M$11) -> 46332 | I14: 3 | J14: A | K14: [26:43] driveway quoted $15-18k; ARB approval before permit
A15: 15 | B15: =IF('Scope Checklist'!A15="","-",'Scope Checklist'!A15) -> 8 | C15: ='Scope Checklist'!D15 -> HOA / ARB approval - Landscaping | D15: After spec sheets | E15: 0 | F15: 15 | G15: =WORKDAY(H7,1+E15,$M$6:$M$11) -> 46314 | H15: =WORKDAY(G15,F15-1,$M$6:$M$11) -> 46332 | I15: 3 | J15: A | K15: [12:39] new entrance, fence + lighting concept
A16: 17 | B16: =IF('Scope Checklist'!A17="","-",'Scope Checklist'!A17) -> 10 | C16: ='Scope Checklist'!D17 -> Certificate of insurance per trade per jurisdiction | D16: 5 wd after provider selection starts | E16: 5 | F16: 10 | G16: =WORKDAY(G11,E16,$M$6:$M$11) -> 46321 | H16: =WORKDAY(G16,F16-1,$M$6:$M$11) -> 46332 | I16: 6 | J16: A | K16: Needed per trade for sub-permits (County, City, HOA)
A17: 18 | B17: =IF('Scope Checklist'!A18="","-",'Scope Checklist'!A18) -> 11 | C17: ='Scope Checklist'!D18 -> Workers compensation per trade | D17: 5 wd after provider selection starts | E17: 5 | F17: 10 | G17: =WORKDAY(G11,E17,$M$6:$M$11) -> 46321 | H17: =WORKDAY(G17,F17-1,$M$6:$M$11) -> 46332 | I17: 4 | J17: A | K17: Collected with COI; ongoing document
A18: 19 | B18: =IF('Scope Checklist'!A19="","-",'Scope Checklist'!A19) -> 12 | C18: ='Scope Checklist'!D19 -> DBPR license per trade | D18: 5 wd after provider selection starts | E18: 5 | F18: 10 | G18: =WORKDAY(G11,E18,$M$6:$M$11) -> 46321 | H18: =WORKDAY(G18,F18-1,$M$6:$M$11) -> 46332 | I18: 3 | J18: A | K18: License check per trade before permit application
A19: 21 | B19: =IF('Scope Checklist'!A21="","-",'Scope Checklist'!A21) -> 14 | C19: ='Scope Checklist'!D21 -> Permits package submittal | D19: After sealed plans + portal + COI | E19: 0 | F19: 3 | G19: =WORKDAY(MAX(H10,H8,H16),1+E19,$M$6:$M$11) -> 46335 | H19: =WORKDAY(G19,F19-1,$M$6:$M$11) -> 46338 | I19: 12 | J19: A | K19: [33:22] city requires independent application per trade under the master project
A20: 20 | B20: =IF('Scope Checklist'!A20="","-",'Scope Checklist'!A20) -> 13 | C20: ='Scope Checklist'!D20 -> Notice of Commencement (NOC) | D20: After package submittal | E20: 0 | F20: 3 | G20: =WORKDAY(H19,1+E20,$M$6:$M$11) -> 46339 | H20: =WORKDAY(G20,F20-1,$M$6:$M$11) -> 46343 | I20: 4 | J20: A | K20: Record before first inspection (FL 713.13); confirm county
A21: 22 | B21: =IF('Scope Checklist'!A22="","-",'Scope Checklist'!A22) -> 15 | C21: ='Scope Checklist'!D22 -> GC master permit - Residential alterations and additions | D21: After package submittal | E21: 0 | F21: 20 | G21: =WORKDAY(H19,1+E21,$M$6:$M$11) -> 46339 | H21: =WORKDAY(G21,F21-1,$M$6:$M$11) -> 46370 | I21: 8 | J21: A | K21: [33:38]-[34:51] master ('papa') permit covers all sub-permits; assumes 1 round of review comments
A22: 23 | B22: =IF('Scope Checklist'!A23="","-",'Scope Checklist'!A23) -> 16 | C22: ='Scope Checklist'!D23 -> Mechanical permit | D22: 5 wd after master permit review starts | E22: 5 | F22: 15 | G22: =WORKDAY(G21,E22,$M$6:$M$11) -> 46346 | H22: =WORKDAY(G22,F22-1,$M$6:$M$11) -> 46370 | I22: 4 | J22: A | K22: [33:19] Mechanical sub-permit; cures AC items
A23: 24 | B23: =IF('Scope Checklist'!A24="","-",'Scope Checklist'!A24) -> 17 | C23: ='Scope Checklist'!D24 -> Electrical permit | D23: 5 wd after master permit review starts | E23: 5 | F23: 15 | G23: =WORKDAY(G21,E23,$M$6:$M$11) -> 46346 | H23: =WORKDAY(G23,F23-1,$M$6:$M$11) -> 46370 | I23: 4 | J23: A | K23: [33:16] Electrical sub-permit
A24: 25 | B24: =IF('Scope Checklist'!A25="","-",'Scope Checklist'!A25) -> 18 | C24: ='Scope Checklist'!D25 -> Plumbing permit | D24: 5 wd after master permit review starts | E24: 5 | F24: 15 | G24: =WORKDAY(G21,E24,$M$6:$M$11) -> 46346 | H24: =WORKDAY(G24,F24-1,$M$6:$M$11) -> 46370 | I24: 4 | J24: A | K24: [34:24] Plumbing sub-permit - critical path for baths
A25: 26 | B25: =IF('Scope Checklist'!A26="","-",'Scope Checklist'!A26) -> 19 | C25: ='Scope Checklist'!D26 -> Fence permit | D25: After package + ARB landscaping | E25: 0 | F25: 10 | G25: =WORKDAY(MAX(H19,H15),1+E25,$M$6:$M$11) -> 46339 | H25: =WORKDAY(G25,F25-1,$M$6:$M$11) -> 46356 | I25: 3 | J25: A + V | K25: [08:44] existing fence to be removed/replaced
A26: 27 | B26: =IF('Scope Checklist'!A27="","-",'Scope Checklist'!A27) -> 20 | C26: ='Scope Checklist'!D27 -> Driveway permit | D26: After package + ARB driveway | E26: 0 | F26: 10 | G26: =WORKDAY(MAX(H19,H14),1+E26,$M$6:$M$11) -> 46339 | H26: =WORKDAY(G26,F26-1,$M$6:$M$11) -> 46356 | I26: 3 | J26: A + V | K26: [26:24] driveway; exterior - not on interior critical path
A27: 28 | B27: =IF('Scope Checklist'!A28="","-",'Scope Checklist'!A28) -> 21 | C27: ='Scope Checklist'!D28 -> Gazebo permit | D27: After package + ARB landscaping | E27: 0 | F27: 10 | G27: =WORKDAY(MAX(H19,H15),1+E27,$M$6:$M$11) -> 46339 | H27: =WORKDAY(G27,F27-1,$M$6:$M$11) -> 46356 | I27: 3 | J27: A | K27: [13:15] BBQ / outdoor area concept
A28: 29 | B28: =IF('Scope Checklist'!A29="","-",'Scope Checklist'!A29) -> 22 | C28: ='Scope Checklist'!D29 -> Garage-door permit | D28: After package + ARB garage door | E28: 0 | F28: 10 | G28: =WORKDAY(MAX(H19,H12),1+E28,$M$6:$M$11) -> 46339 | H28: =WORKDAY(G28,F28-1,$M$6:$M$11) -> 46356 | I28: 3 | J28: A | K28: Garage door replacement permit
A29: 30 | B29: =IF('Scope Checklist'!A30="","-",'Scope Checklist'!A30) -> 23 | C29: ='Scope Checklist'!D30 -> Demolition & Waste Management | D29: Baseline start -> end of primer (N5) | E29: 0 | F29: =NETWORKDAYS(G29,H29,$M$6:$M$11) -> 76 | G29: =$C$3 -> 46300 | H29: =H41 -> 46413 | I29: 10 | J29: A | K29: Dumpster kept through demo/structure phase
A30: 31 | B30: =IF('Scope Checklist'!A31="","-",'Scope Checklist'!A31) -> 24 | C30: ='Scope Checklist'!D31 -> Utilities | D30: Baseline start -> closeout | E30: 0 | F30: - | G30: =$C$3 -> 46300 | H30: Ongoing | I30: 2 | J30: A | K30: Ongoing - autopay
A31: INTERIOR - DEMO/STRUCTURE
A32: 35 | B32: =IF('Scope Checklist'!A35="","-",'Scope Checklist'!A35) -> N1 | C32: ='Scope Checklist'!D35 -> Site protection + inventory (windows, railings, outlets, switches, smoke detectors) | D32: Baseline start | E32: 0 | F32: 2 | G32: =$C$3 -> 46300 | H32: =WORKDAY(G32,F32-1,$M$6:$M$11) -> 46301 | I32: 12 | J32: A + V | K32: [16:10]-[17:08] protect windows/railings, inventory + cover outlets/switches/smoke detectors; acta: before any new intervention
A33: 36 | B33: =IF('Scope Checklist'!A36="","-",'Scope Checklist'!A36) -> N2 | C33: ='Scope Checklist'!D36 -> Structural engineering review - removed interior walls / truss bearing | D33: Baseline start (feeds A&E design) | E33: 0 | F33: 8 | G33: =$C$3 -> 46300 | H33: =WORKDAY(G33,F33-1,$M$6:$M$11) -> 46309 | I33: 8 | J33: A / Sub | K33: [14:41]-[15:36] load-bearing check of removed walls; trusses bear on perimeter - needs sealed letter
A34: 37 | B34: =IF('Scope Checklist'!A37="","-",'Scope Checklist'!A37) -> 56 | C34: ='Scope Checklist'!D37 -> Popcorn ceiling removal - flat finish & skin coat | D34: After site protection | E34: 0 | F34: 8 | G34: =WORKDAY(H32,1+E34,$M$6:$M$11) -> 46302 | H34: =WORKDAY(G34,F34-1,$M$6:$M$11) -> 46311 | I34: 64 | J34: Sub | K34: No permit needed; asbestos test first (industry practice); final skim folded into drywall final
A35: 38 | B35: =IF('Scope Checklist'!A38="","-",'Scope Checklist'!A38) -> 53 | C35: ='Scope Checklist'!D38 -> Framing repairs / new partitions | D35: After GC master permit issued + engineer letter | E35: 0 | F35: 5 | G35: =WORKDAY(MAX(H21,H33),1+E35,$M$6:$M$11) -> 46371 | H35: =WORKDAY(G35,F35-1,$M$6:$M$11) -> 46377 | I35: 60 | J35: V | K35: [14:41] engineer approval; permitted work cannot start before issuance
A36: 39 | B36: =IF('Scope Checklist'!A39="","-",'Scope Checklist'!A39) -> N3 | C36: ='Scope Checklist'!D39 -> Slab trench patch after underground plumbing (baths/kitchen) + slab inspection | D36: After underground DWV inspection PASS (N8) | E36: 0 | F36: 3 | G36: =WORKDAY(H57,1+E36,$M$6:$M$11) -> 46377 | H36: =WORKDAY(G36,F36-1,$M$6:$M$11) -> 46379 | I36: 16 | J36: V | K36: [52:36]-[53:16] underground inspection, then slab + plumbing inspections simultaneously
A37: 40 | B37: =IF('Scope Checklist'!A40="","-",'Scope Checklist'!A40) -> 57 | C37: ='Scope Checklist'!D40 -> Concrete slab repair + tile infill under AC unit | D37: After mechanical permit | E37: 0 | F37: 2 | G37: =WORKDAY(H22,1+E37,$M$6:$M$11) -> 46371 | H37: =WORKDAY(G37,F37-1,$M$6:$M$11) -> 46372 | I37: 12 | J37: V / Sub | K37: Existing scope note; same crew as N3
A38: 41 | B38: =IF('Scope Checklist'!A41="","-",'Scope Checklist'!A41) -> N4 | C38: ='Scope Checklist'!D41 -> Framing + MEP rough-in inspections (pre-cover milestone) | D38: After framing, slabs, panel, electrical rough-in (N7), plumbing top-out (N9) + duct modifications (N10) | E38: 0 | F38: 5 | G38: =WORKDAY(MAX(H35,H36,H37,H46,H47,H58,H63),1+E38,$M$6:$M$11) -> 46387 | H38: =WORKDAY(G38,F38-1,$M$6:$M$11) -> 46394 | I38: 8 | J38: A | K38: [35:22]-[36:34] each step waits for next-day inspector; buffer for 1 re-inspection
A39: 42 | B39: =IF('Scope Checklist'!A42="","-",'Scope Checklist'!A42) -> - | C39: ='Scope Checklist'!D42 -> Drywall repair / install & finish. 2nd phase | D39: After inspections PASS | E39: 0 | F39: 5 | G39: =WORKDAY(H38,1+E39,$M$6:$M$11) -> 46395 | H39: =WORKDAY(G39,F39-1,$M$6:$M$11) -> 46401 | I39: 80 | J39: V | K39: Hang + tape new partitions; corner bead
A40: 43 | B40: =IF('Scope Checklist'!A43="","-",'Scope Checklist'!A43) -> - | C40: ='Scope Checklist'!D43 -> Drywall repair / install & finish. Final phase | D40: After drywall 2nd phase | E40: 0 | F40: 5 | G40: =WORKDAY(H39,1+E40,$M$6:$M$11) -> 46402 | H40: =WORKDAY(G40,F40-1,$M$6:$M$11) -> 46408 | I40: 60 | J40: V | K40: Finish, sand, ceiling final skim
A41: 44 | B41: =IF('Scope Checklist'!A44="","-",'Scope Checklist'!A44) -> N5 | C41: ='Scope Checklist'!D44 -> Surface prep - primer on walls + ceilings | D41: After drywall final | E41: 0 | F41: 3 | G41: =WORKDAY(H40,1+E41,$M$6:$M$11) -> 46409 | H41: =WORKDAY(G41,F41-1,$M$6:$M$11) -> 46413 | I41: 40 | J41: H | K41: [18:17]-[19:44] primer coat on walls + ceilings before wet trades
A42: LINK TO FINISH TRADES (PROVISIONAL)
A43: - | B43: - | C43: Finish trades ready for MEP trim (milestone) | D43: PROVISIONAL: primer end + 20 wd - re-link to Kitchen/Bath rows once scheduled | E43: 20 | F43: 1 | G43: =WORKDAY(H41,1+E43,$M$6:$M$11) -> 46442 | H43: =WORKDAY(G43,F43-1,$M$6:$M$11) -> 46442 | I43: - | J43: A | K43: Sheet data: cabinets install 1-2 d, bath tile ~10 d, countertops field measure + 5-d fabrication + install = ~20 wd before MEP trim
A44: INTERIOR - ELECTRICAL
A45: 48 | B45: =IF('Scope Checklist'!A48="","-",'Scope Checklist'!A48) -> N6 | C45: ='Scope Checklist'!D48 -> Make-safe exposed wiring from demolition (cap, label, temp lighting) | D45: Baseline start (safety, before trades return) | E45: 0 | F45: 1 | G45: =$C$3 -> 46300 | H45: =WORKDAY(G45,F45-1,$M$6:$M$11) -> 46300 | I45: 6 | J45: Sub | K45: [14:34]-[14:41] exposed cables after wall removal
A46: 49 | B46: =IF('Scope Checklist'!A49="","-",'Scope Checklist'!A49) -> 60 | C46: ='Scope Checklist'!D49 -> Electrical panel change out | D46: After electrical permit | E46: 0 | F46: 2 | G46: =WORKDAY(H23,1+E46,$M$6:$M$11) -> 46371 | H46: =WORKDAY(G46,F46-1,$M$6:$M$11) -> 46372 | I46: 12 | J46: A + V | K46: Existing scope; coordinate utility disconnect/reconnect; inspected with rough-in (N4)
A47: 50 | B47: =IF('Scope Checklist'!A50="","-",'Scope Checklist'!A50) -> N7 | C47: ='Scope Checklist'!D50 -> Electrical rough-in - relocated boxes, new kitchen/bath circuits | D47: After electrical permit + framing | E47: 0 | F47: 5 | G47: =WORKDAY(MAX(H23,H35,H45),1+E47,$M$6:$M$11) -> 46378 | H47: =WORKDAY(G47,F47-1,$M$6:$M$11) -> 46386 | I47: 60 | J47: Sub | K47: [12:07]-[12:38] open kitchen, removed partitions; [33:16] electrical sub-permit
A48: 51 | B48: =IF('Scope Checklist'!A51="","-",'Scope Checklist'!A51) -> 61 | C48: ='Scope Checklist'!D51 -> Outlets, switches, GFCI/AFCI | D48: Trim window (PROVISIONAL anchor) | E48: 0 | F48: 3 | G48: =WORKDAY(H43,1+E48,$M$6:$M$11) -> 46443 | H48: =WORKDAY(G48,F48-1,$M$6:$M$11) -> 46447 | I48: 24 | J48: Sub | K48: Existing scope: incl. dedicated fridge + oven outlets
A49: 52 | B49: =IF('Scope Checklist'!A52="","-",'Scope Checklist'!A52) -> 62 | C49: ='Scope Checklist'!D52 -> Recessed lighting (LED) | D49: With outlets (same electrician visit) | E49: 0 | F49: 2 | G49: =WORKDAY(G48,E49,$M$6:$M$11) -> 46443 | H49: =WORKDAY(G49,F49-1,$M$6:$M$11) -> 46444 | I49: 12 | J49: Sub | K49: Cans set at rough-in (N7); trims after paint
A50: 53 | B50: =IF('Scope Checklist'!A53="","-",'Scope Checklist'!A53) -> 63 | C50: ='Scope Checklist'!D53 -> Ceiling fans | D50: 1 wd after outlets start | E50: 1 | F50: 2 | G50: =WORKDAY(G48,E50,$M$6:$M$11) -> 46444 | H50: =WORKDAY(G50,F50-1,$M$6:$M$11) -> 46447 | I50: 12 | J50: Sub | K50: Existing scope: patio, master, bed 2, bed 3, living
A51: 54 | B51: =IF('Scope Checklist'!A54="","-",'Scope Checklist'!A54) -> 64 | C51: ='Scope Checklist'!D54 -> Dining fixture (kitchen chandelier) | D51: 2 wd after outlets start | E51: 2 | F51: 1 | G51: =WORKDAY(G48,E51,$M$6:$M$11) -> 46447 | H51: =WORKDAY(G51,F51-1,$M$6:$M$11) -> 46447 | I51: 3 | J51: Sub | K51: Existing scope: reposition box at rough-in
A52: 55 | B52: =IF('Scope Checklist'!A55="","-",'Scope Checklist'!A55) -> 65 | C52: ='Scope Checklist'!D55 -> LED mirrors - install | D52: After outlets (vanities + tile in place) | E52: 0 | F52: 1 | G52: =WORKDAY(H48,1+E52,$M$6:$M$11) -> 46448 | H52: =WORKDAY(G52,F52-1,$M$6:$M$11) -> 46448 | I52: 4 | J52: V | K52: Existing scope
A53: 56 | B53: =IF('Scope Checklist'!A56="","-",'Scope Checklist'!A56) -> 66 | C53: ='Scope Checklist'!D56 -> Smoke / CO detectors - replace all | D53: After outlets | E53: 0 | F53: 1 | G53: =WORKDAY(H48,1+E53,$M$6:$M$11) -> 46448 | H53: =WORKDAY(G53,F53-1,$M$6:$M$11) -> 46448 | I53: 4 | J53: V > A | K53: [16:49]-[16:55] detectors covered during works; replace at trim
A54: 57 | B54: =IF('Scope Checklist'!A57="","-",'Scope Checklist'!A57) -> 67 | C54: ='Scope Checklist'!D57 -> Doorbell / smart doorbell | D54: After outlets | E54: 0 | F54: 1 | G54: =WORKDAY(H48,1+E54,$M$6:$M$11) -> 46448 | H54: =WORKDAY(G54,F54-1,$M$6:$M$11) -> 46448 | I54: 2 | J54: Sub | K54: Existing scope
A55: 47 | B55: =IF('Scope Checklist'!A47="","-",'Scope Checklist'!A47) -> 59 | C55: ='Scope Checklist'!D47 -> Electrical contract - overall | D55: Umbrella: make-safe start -> last electrical item | E55: 0 | F55: =NETWORKDAYS(G55,H55,$M$6:$M$11) -> 101 | G55: =G45 -> 46300 | H55: =MAX(H46,H47,H48,H49,H50,H51,H52,H53,H54) -> 46448 | I55: - | J55: Sub | K55: Contract envelope; hours carried by the detail rows
A56: INTERIOR - PLUMBING
A57: 60 | B57: =IF('Scope Checklist'!A60="","-",'Scope Checklist'!A60) -> N8 | C57: ='Scope Checklist'!D60 -> Underground DWV rough-in (baths/kitchen) incl. P-traps + underground inspection PASS | D57: After plumbing permit (3 wd work + 1 wd inspection) | E57: 0 | F57: 4 | G57: =WORKDAY(H24,1+E57,$M$6:$M$11) -> 46371 | H57: =WORKDAY(G57,F57-1,$M$6:$M$11) -> 46374 | I57: 32 | J57: V | K57: [50:25]-[52:36] missing trap -> sewer gas -> shower rebuilt; [52:23] underground inspection before slab
A58: 61 | B58: =IF('Scope Checklist'!A61="","-",'Scope Checklist'!A61) -> N9 | C58: ='Scope Checklist'!D61 -> Water supply rough-in / top-out (shower valves, toilets, kitchen, fridge line) + pressure test | D58: After slab patch (N3) | E58: 0 | F58: 3 | G58: =WORKDAY(H36,1+E58,$M$6:$M$11) -> 46384 | H58: =WORKDAY(G58,F58-1,$M$6:$M$11) -> 46386 | I58: 24 | J58: V | K58: [53:00]-[53:16] inspector checks penetrations + blocking
A59: 62 | B59: =IF('Scope Checklist'!A62="","-",'Scope Checklist'!A62) -> 71 | C59: ='Scope Checklist'!D62 -> Plumbing inventory check - supply lines, drainage, P-traps | D59: After top-out (quantities known) | E59: 0 | F59: 2 | G59: =WORKDAY(H58,1+E59,$M$6:$M$11) -> 46387 | H59: =WORKDAY(G59,F59-1,$M$6:$M$11) -> 46391 | I59: 6 | J59: V | K59: Buy P-traps/supply lines early; only long-lead item is kitchen cabinets [28:29]
A60: 63 | B60: =IF('Scope Checklist'!A63="","-",'Scope Checklist'!A63) -> 69 | C60: ='Scope Checklist'!D63 -> Final plumbing completion labor | D60: Trim window (PROVISIONAL anchor) | E60: 0 | F60: 3 | G60: =WORKDAY(H43,1+E60,$M$6:$M$11) -> 46443 | H60: =WORKDAY(G60,F60-1,$M$6:$M$11) -> 46447 | I60: 24 | J60: V | K60: Existing scope: ~3 days at Victor's daily rate
A61: 64 | B61: =IF('Scope Checklist'!A64="","-",'Scope Checklist'!A64) -> 72 | C61: ='Scope Checklist'!D64 -> Angle stops and supply lines throughout | D61: With final plumbing labor | E61: 0 | F61: 2 | G61: =WORKDAY(G60,E61,$M$6:$M$11) -> 46443 | H61: =WORKDAY(G61,F61-1,$M$6:$M$11) -> 46444 | I61: 8 | J61: V | K61: Existing scope
A62: INTERIOR - HVAC
A63: 69 | B63: =IF('Scope Checklist'!A69="","-",'Scope Checklist'!A69) -> N10 | C63: ='Scope Checklist'!D69 -> Duct modifications - removed partitions, kitchen hood + bath exhaust ducting | D63: After mechanical permit + framing | E63: 0 | F63: 3 | G63: =WORKDAY(MAX(H22,H35),1+E63,$M$6:$M$11) -> 46378 | H63: =WORKDAY(G63,F63-1,$M$6:$M$11) -> 46384 | I63: 24 | J63: Sub | K63: [33:19] mechanical sub-permit; [12:07] removed partitions; must be in before N4 inspection
A64: 70 | B64: =IF('Scope Checklist'!A70="","-",'Scope Checklist'!A70) -> 77 | C64: ='Scope Checklist'!D70 -> Ductwork inspection / repair / clean | D64: After primer (dusty work finished) | E64: 0 | F64: 2 | G64: =WORKDAY(H41,1+E64,$M$6:$M$11) -> 46414 | H64: =WORKDAY(G64,F64-1,$M$6:$M$11) -> 46415 | I64: 16 | J64: Sub | K64: Industry practice: clean ducts after sanding, not before
A65: 71 | B65: =IF('Scope Checklist'!A71="","-",'Scope Checklist'!A71) -> 75 | C65: ='Scope Checklist'!D71 -> HVAC coil cleaning | D65: After primer (with duct cleaning visit) | E65: 0 | F65: 1 | G65: =WORKDAY(H41,1+E65,$M$6:$M$11) -> 46414 | H65: =WORKDAY(G65,F65-1,$M$6:$M$11) -> 46414 | I65: 4 | J65: Sub | K65: Existing scope: part of maintenance line
A66: 72 | B66: =IF('Scope Checklist'!A72="","-",'Scope Checklist'!A72) -> 76 | C66: ='Scope Checklist'!D72 -> HVAC coolant refill service | D66: Same visit as coil cleaning | E66: 0 | F66: 1 | G66: =WORKDAY(G65,E66,$M$6:$M$11) -> 46414 | H66: =WORKDAY(G66,F66-1,$M$6:$M$11) -> 46414 | I66: 3 | J66: Sub | K66: Existing scope: part of maintenance line
A67: 73 | B67: =IF('Scope Checklist'!A73="","-",'Scope Checklist'!A73) -> 78 | C67: ='Scope Checklist'!D73 -> AC diffusers | D67: Trim window (PROVISIONAL anchor) | E67: 0 | F67: 1 | G67: =WORKDAY(H43,1+E67,$M$6:$M$11) -> 46443 | H67: =WORKDAY(G67,F67-1,$M$6:$M$11) -> 46443 | I67: 4 | J67: A | K67: Existing scope: purchase early, install after final paint
A68: 74 | B68: =IF('Scope Checklist'!A74="","-",'Scope Checklist'!A74) -> 79 | C68: ='Scope Checklist'!D74 -> Thermostat | D68: Trim window (PROVISIONAL anchor) | E68: 0 | F68: 1 | G68: =WORKDAY(H43,1+E68,$M$6:$M$11) -> 46443 | H68: =WORKDAY(G68,F68-1,$M$6:$M$11) -> 46443 | I68: 2 | J68: V | K68: Existing scope
A69: 68 | B69: =IF('Scope Checklist'!A68="","-",'Scope Checklist'!A68) -> 74 | C69: ='Scope Checklist'!D68 -> HVAC maintenance + concrete slab repair | D69: Umbrella: AC slab repair start -> last maintenance item | E69: 0 | F69: =NETWORKDAYS(G69,H69,$M$6:$M$11) -> 30 | G69: =G37 -> 46371 | H69: =MAX(H37,H63,H64,H65,H66) -> 46415 | I69: - | J69: A / Sub | K69: Contract envelope ($2,100); hours carried by the detail rows
A70: KITCHEN
A71: 76 | B71: =IF('Scope Checklist'!A76="","-",'Scope Checklist'!A76) -> N11 | C71: ='Scope Checklist'!D76 -> Cabinet order - field-verify dimensions, PO + fabrication (3-4 wk) | D71: After framing (dimensions fixed) + provider selection | E71: 0 | F71: 20 | G71: =WORKDAY(MAX(H35,H11),1+E71,$M$6:$M$11) -> 46378 | H71: =WORKDAY(G71,F71-1,$M$6:$M$11) -> 46408 | I71: 6 | J71: A | K71: [28:00]-[29:44] fabrication 3-4 wk; cash constraint -> order just in time; [13:21] layout needs Jaime approval
A72: 77 | B72: =IF('Scope Checklist'!A77="","-",'Scope Checklist'!A77) -> 80 | C72: ='Scope Checklist'!D77 -> Kitchen cabinets + bathroom vanities (combined contract) | D72: After primer + cabinet delivery | E72: 0 | F72: 2 | G72: =WORKDAY(MAX(H41,H71),1+E72,$M$6:$M$11) -> 46414 | H72: =WORKDAY(G72,F72-1,$M$6:$M$11) -> 46415 | I72: 16 | J72: A + V | K72: Sheet: install by manufacturer 1-2 days max; A + V verify quality on site. Vanities follow the bath sequence
A73: 78 | B73: =IF('Scope Checklist'!A78="","-",'Scope Checklist'!A78) -> 81 | C73: ='Scope Checklist'!D78 -> Stone countertops + backsplash (kitchen + baths) | D73: After cabinets set (field template) | E73: 0 | F73: 8 | G73: =WORKDAY(H72,1+E73,$M$6:$M$11) -> 46416 | H73: =WORKDAY(G73,F73-1,$M$6:$M$11) -> 46427 | I73: 12 | J73: A / M | K73: Sheet: template after cabinets set -> ~5 business days fabrication -> install 1-2 days; same slab for vanities/thresholds saves $
A74: 79 | B74: =IF('Scope Checklist'!A79="","-",'Scope Checklist'!A79) -> 82 | C74: ='Scope Checklist'!D79 -> Kitchen sink - purchase | D74: 5 wd into cabinet fabrication (must be on site for template) | E74: 5 | F74: 5 | G74: =WORKDAY(G71,E74,$M$6:$M$11) -> 46387 | H74: =WORKDAY(G74,F74-1,$M$6:$M$11) -> 46394 | I74: 3 | J74: A | K74: Undermount sink needed for countertop cut-out
A75: 80 | B75: =IF('Scope Checklist'!A80="","-",'Scope Checklist'!A80) -> 83 | C75: ='Scope Checklist'!D80 -> Kitchen faucet | D75: 5 wd into cabinet fabrication | E75: 5 | F75: 5 | G75: =WORKDAY(G71,E75,$M$6:$M$11) -> 46387 | H75: =WORKDAY(G75,F75-1,$M$6:$M$11) -> 46394 | I75: 2 | J75: V > A | K75: Verify if already purchased; faucet hole count for template
A76: 81 | B76: =IF('Scope Checklist'!A81="","-",'Scope Checklist'!A81) -> 84 | C76: ='Scope Checklist'!D81 -> Appliance package - purchase, transport, install | D76: 5 wd into cabinet fabrication (specs frozen before order) | E76: 5 | F76: 10 | G76: =WORKDAY(G71,E76,$M$6:$M$11) -> 46387 | H76: =WORKDAY(G76,F76-1,$M$6:$M$11) -> 46401 | I76: 16 | J76: A | K76: Sheet: appliance package; fridge + cooktop + hood dimensions drive cabinet order and countertop cut-outs
A77: 82 | B77: =IF('Scope Checklist'!A82="","-",'Scope Checklist'!A82) -> N12 | C77: ='Scope Checklist'!D82 -> Appliance install + hook-ups (oven, cooktop, DW, disposal, hood, fridge line) | D77: After countertops + electrical/plumbing trim | E77: 0 | F77: 2 | G77: =WORKDAY(MAX(H73,H48,H60),1+E77,$M$6:$M$11) -> 46448 | H77: =WORKDAY(G77,F77-1,$M$6:$M$11) -> 46449 | I77: 12 | J77: V | K77: Dedicated circuits from rough-in (N7); DW/disposal need final plumbing
A78: 83 | B78: =IF('Scope Checklist'!A83="","-",'Scope Checklist'!A83) -> 86 | C78: ='Scope Checklist'!D83 -> Under-cabinet lighting | D78: With electrical trim (after countertops/backsplash) | E78: 0 | F78: 1 | G78: =WORKDAY(G48,E78,$M$6:$M$11) -> 46443 | H78: =WORKDAY(G78,F78-1,$M$6:$M$11) -> 46443 | I78: 4 | J78: A | K78: Existing scope: transformer + LED strip / puck lights
C80: Milestones
C81: Permits issued (GC master + M/E/P) | H81: =MAX(H21,H22,H23,H24) -> 46370
C82: Framing + MEP rough-in inspections passed | H82: =H38 -> 46394
C83: Demo/Structure phase complete (primer done) | H83: =H41 -> 46413
C84: Underground plumbing inspection passed | H84: =H57 -> 46374
C85: Finish trades ready for MEP trim (PROVISIONAL) | H85: =H43 -> 46442
C86: Electrical complete (trim) | H86: =H55 -> 46448
C87: Plumbing complete (trim) | H87: =MAX(H60,H61) -> 46447
C88: HVAC complete (diffusers + thermostat) | H88: =MAX(H67,H68) -> 46443
C89: Kitchen countertops installed | H89: =H73 -> 46427
C90: Kitchen complete (appliances installed) | H90: =MAX(H77,H78) -> 46449
C91: Total effort - Pre-Construction (hrs) | I91: =SUM(I7:I30) -> 217
C92: Total effort - Demo/Structure (hrs) | I92: =SUM(I32:I41) -> 360
C93: Total effort - Electrical (hrs) | I93: =SUM(I45:I55) -> 139
C94: Total effort - Plumbing (hrs) | I94: =SUM(I57:I61) -> 94
C95: Total effort - HVAC (hrs) | I95: =SUM(I63:I69) -> 53
C96: Total effort - Kitchen (hrs) | I96: =SUM(I71:I78) -> 71

Sheet 3-Week Plan
A1: 3-WEEK EXECUTION PLAN - A = Andres | V = Victor | H = Hans | S = Sub | M = Martin (stone) | G = Gino (glass)
A2: Codes match 'Exec Order' column on Scope Checklist
A4: WEEK 1 - UNBLOCK: permits, inspections, decisions, purchases, wet-area rough
A5: Code | B5: Owner | C5: Task
A6: W1-01 | B6: A | C6: Record NOC with Broward County (required before first inspection)
A7: W1-02 | B7: A | C7: Push issuance: GC master permit + plumbing sub-permit (bathrooms) - CRITICAL PATH for shower pan inspection
A8: W1-03 | B8: A | C8: Driveway permit resubmission
A9: W1-04 | B9: A | C9: Windows/doors/garage door permit - push forward; schedule inspection
A10: W1-05 | B10: A + V | C10: Electrical permit: A paperwork; V provides labels for panel, amperage, service
A11: W1-06 | B11: A + V | C11: Mechanical permit (cure AC violation): A paperwork + qualifier ~$800 fee; V photographs equipment label (model + tonnage)
A12: W1-07 | B12: - | C12: Roofing - COMPLETE, no further action
A13: W1-08 | B13: V | C13: Master bath drywall: finish, compound, sand, paint; detach vanity + back wall; confirm faucet height + countertop height for sink type selection
A14: W1-09 | B14: A / V / Sub | C14: HVAC: A hires service (coil clean, coolant, filter, duct check); V demos closet tile + installs new tile at unit
A15: W1-10 | B15: A + V | C15: Panel installed: V adds labels to cover + identifies amperage/service; A schedules + passes inspection
A16: W1-11 | B16: A + V | C16: Mon Jul 6, 11 AM - both at Noel cabinet quality appointment -> release manufacturer install (1-2 days); verify vanities same visit
... A26: W1-21 | B26: Sub | C26: Bathtub electrical connection - roughed + READY FOR INSPECTION (in electrical contract); tub sets W2 after inspections pass
A28: WEEK 2 - PRODUCTION: tile marathon, electrical finish, exterior, paint
A29: Code | B29: Owner | C29: Task
A30: W2-01 | B30: S | C30: Sub STARTS bathroom tile - both baths (~10 days, runs into W3). Only after W1-18 + inspections. Also open exhaust fan holes so fans are install-ready
A31: W2-02 | B31: Sub / V | C31: Electrical finish: outlets/switches/GFCI (incl. dedicated fridge + oven outlets), ceiling fans, chandelier box + install, floodlight, kitchen LED, patio recessed fix, doorbell. V: LED niches ASAP - confirm inventory or order supply (before tile)
A32: W2-03 | B32: V | C32: Victor plumbing (~3 days): angle stops, supply lines; inventory check - supply lines, drainage, P-traps for kitchen + bath faucets, toilets (list + purchase gaps)
A33: W2-04 | B33: S / H | C33: S: stucco texture (A finds stucco sub); H: paint over textured areas
A34: W2-05 | B34: H / A | C34: H: fascia + trim repaint (change color), soffit vents install + paint, remove old mesh; A: confirm color choice
A35: W2-06 | B35: A / S | C35: Pavers: S installs + seals; A coordinates sub, arranges delivery, processes permit, sets final quote appointment, tries to meet on site Monday
A36: W2-07 | B36: A / S | C36: ENTRY TILE (walkway stays concrete - part of pavers): A selects tile; S installs at same time as shower tile; MUST happen before pavers
A37: W2-08 | B37: V / H / S | C37: Patio drainage: V fixes drain; H makes hole + covers with soil; S (tile) fixes broken piece
A38: W2-09 | B38: S / A | C38: S: sprinkler repair, timer verify, build pipelines as needed; A: buy or inquire pump box cover
A39: W2-10 | B39: S | C39: Tree trimming, possible side palm removal, landscape build-out
A40: W2-11 | B40: V+H / A | C40: Garage door swap with Jupiter unit + opener; A: rent van for transport
... A50: W2-21 | B50: A > V | C50: Laundry shelf + garage shelf: A selects; V installs
A52: WEEK 3 - FINISH + CLOSE: stone, glass, fixtures, inspections
A53: Code | B53: Owner | C53: Task
A54: W3-01 | B54: M | C54: Countertop + backsplash install (~5 days after quote; subject to stone purchase + delivery availability); thresholds + bench tops
A55: W3-02 | B55: V | C55: Install faucets + sinks - both baths + kitchen (verify vanity heights). (Toilets moved to W1-20)
A56: W3-03 | B56: G / A / V | C56: Master: Gino quotes + installs glass. Secondary: existing inventory glass w/ black hardware (A provides); V confirms width
A57: W3-04 | B57: V | C57: Install LED mirrors + exhaust fans (master duct coupling; secondary power supply); bath hardware (purchased W1)
A58: W3-06 | B58: V | C58: Appliances: final installs/connections as acquired (transport + install runs W1-W2)
A59: W3-08 | B59: A + V | C59: Blinds: V confirms measurements; A selects; approval needed; install
A60: W3-11 | B60: S | C60: Grass (front) + landscape build-out - timing W1-W3 per design decision + availability
A61: W3-12 | B61: A > V | C61: Small items: house numbers/mailbox, screen door alignment/lock, exterior handles; interior garage door - A purchases, V installs
A62: W3-13 | B62: A + H | C62: Organize storage; transport tool box to property
A63: W3-14 | B63: A | C63: FINAL INSPECTIONS: windows/doors, electrical, plumbing, mechanical (AC violation cured)
A64: W3-15 | B64: A | C64: Permit closeout - all permits, CO/CC
... A69: Moved | B69: - | C69: Earlier: toilets -> W1-20 (V); tub set -> W2-17 (V); closets -> W2-18 (A+V); trim/doors -> W2-14 (H); corner bead -> W2-19 (V); LED mirror/hardware/outlet purchases -> W1-14 (A)
A71: Critical path: permits -> W1-18 shower sequence -> S tile (10 days) -> Gino measure/fab -> glass install. Stone chain: Jul 4 Martin quote -> Jul 6 cabinets -> field measure -> 5-day fab -> W3-01 install. Entry tile before pavers; pavers permit-dependent.

Sheet Cost Summary
A1: PROJECT STATUS & COST SUMMARY
A2: 101 W Bayridge Dr, Weston, FL 33326 - per uploaded cost summary
A4: Category | B4: Item | C4: Total Cost | D4: Credits | E4: Balance Due | F4: Permit / Inspection Status | G4: Remaining Work
A5: Roofing | B5: Roof Replacement | C5: 30297 | E5: 0 | F5: Final Inspection Pending | G5: None
A6: Windows | B6: Window Installation | C6: 19825.36 | D6: 300 | E6: 0 | F6: Final Inspection Pending | G6: Decorative door panels + close-out trim
A7: Electrical | B7: Electrical Work | C7: 14000 | D7: 0 | E7: 7000 | F7: Final Inspection Pending | G7: Light fixtures + fans, all outlets + switches, kitchen chandelier, exterior floodlight, kitchen LED, bath exhaust fans, bathtub electrical, LED mirrors
A8: Plumbing | B8: Final Plumbing (labor factored separately) | D8: 0 | E8: 1500 | F8: Final Inspection Pending | G8: ~3 days labor at Victor's daily rate
A9: Tile Work | B9: Bathroom Tile Installation (labor) | D9: 0 | E9: 3500 | F9: N/A | G9: Complete bathroom tile install, both baths; ~10 days
A10: Shower Glass | B10: Shower Glass Fabrication + Install | C10: 3000 | D10: 0 | E10: 3000 | F10: N/A | G10: Fabrication ~4 days; install 1-2 days
A11: Cabinetry | B11: Kitchen Cabinets + Bathroom Vanities | C11: 21750 | D11: 0 | E11: 4875 | F11: N/A | G11: Install by manufacturer, 1-2 days max
A12: Countertops | B12: Stone Countertops + Backsplash | C12: 5925 | D12: 0 | E12: 4500 | F12: N/A | G12: $50-$75/sq ft; kitchen ~35sf counter + ~25sf backsplash; bath2 ~8sf, master ~11sf; fab ~5 days; cabinets must be installed before field measure
A13: Appliances | B13: Appliance Purchase Package | C13: 9100 | D13: 0 | E13: 9100 | F13: N/A | G13: Samsung oven+micro $3,700; cooktop $650; DW $500; hood $500; disposal $250; wine cooler $450; fridge $1,800; W+D $1,250
A14: Landscaping | B14: Sprinkler System | D14: 0 | E14: 500 | F14: N/A | G14: Check heads; verify timer, all 3 zones; replace broken pipes
A15: Landscaping | B15: Front Yard Design | D15: 0 | E15: 2500 | F15: N/A | G15: TBD
A16: Landscaping | B16: Backyard Design | D16: 0 | F16: Pending Review | G16: Deck proposal under consideration; permit may be required by deck size
A17: Landscaping | B17: Side Yard Design | D17: 0 | F17: N/A | G17: TBD
A18: Landscaping | B18: Grass Installation (Front Only) | D18: 0 | F18: N/A | G18: TBD
A19: Driveway + Walkway | B19: Pavers | C19: 10000 | D19: 0 | E19: 10000 | F19: Permit Required | G19: Labor $6,200-$7,000; material ~$2,000; sealant $2,000; permit 3-5 day review; HOA 2-3 days; 2-3 days on site
A20: Driveway | B20: Asphalt Overlay | C20: 3000 | D20: 0 | E20: 3000 | F20: Permit Required | G20: Permit 3-5 day review; HOA 2-3 days; 2-3 days labor; no concrete walkway
A21: Walkway | B21: Tile Installation Proposal | C21: 2000 | D21: 0 | E21: 1500 | F21: TBD | G21: Material ~$600; Victor concrete repair 2 days @$300/day; root cut; leveling; tile installer 2 days $600-$800
A22: Drainage | B22: Patio Drain Inspection + Repair | D22: 0 | F22: N/A | G22: Inspect + repair drain; side drain cover; replace metal screen piece; protect adjacent tile
A23: HVAC | B23: HVAC Maintenance + Concrete Slab Repair | C23: 2100 | D23: 0 | E23: 2000 | F23: Permit + Inspection Required | G23: Maintenance; slab under equipment needs repair; cost depends in-house vs full replace
A24: Garage Door | B24: Hurricane-Rated Garage Door Replacement | C24: 7500 | D24: 0 | E24: 4500 | F24: Permit Required | G24: HVHZ/wind-load compliant 16x7 insulated steel; incl. permit, removal, reinforced tracks, wind-load hardware, motor reconnect, final inspection
B25: TOTAL BALANCE DUE (pending items to 100% completion) | E25: =SUM(E5:E24) -> 57475
B26: Note: source PDF states $52,975 pending total; line items above sum higher - reconcile (likely asphalt overlay/walkway as alternates or garage door exclusion)
A28: PROJECT SPEND SUMMARY
B29: 2025 | C29: 2026 | D29: Total
A30: Checking account (labor + materials + utilities + HOA + services) | B30: 107414.33 | C30: 24481.58 | D30: =B30+C30 -> 131895.91
A31: Credit card (labor + materials + utilities + HOA + services) | B31: 22180.93 | C31: 12294.9 | D31: =B31+C31 -> 34475.83
A32: SUBTOTAL | B32: =SUM(B30:B31) -> 129595.26 | C32: =SUM(C30:C31) -> 36776.48 | D32: =B32+C32 -> 166371.74
A33: PROJECT TOTAL TO DATE | D33: =D32 -> 166371.74

Sheet Summary
A1: RENOVATION SUMMARY BY CATEGORY
A2: 101 W Bayridge Dr, Weston, FL 33326
A4: Category | B4: Items | C4: Pending | D4: In Progress | E4: Complete | F4: Not Needed | G4: Total Cost | H4: Balance Due
A5: Pre-Construction | B5: =COUNTIF('Scope Checklist'!$B$6:$B$149,A5) -> 25 | C5: =COUNTIFS('Scope Checklist'!$B$6:$B$149,A5,'Scope Checklist'!$E$6:$E$149,"Pending") -> 22 | D5: =COUNTIFS('Scope Checklist'!$B$6:$B$149,A5,'Scope Checklist'!$E$6:$E$149,"In Progress") -> 2 | E5: =COUNTIFS('Scope Checklist'!$B$6:$B$149,A5,'Scope Checklist'!$E$6:$E$149,"Complete") -> 1 | F5: =COUNTIFS('Scope Checklist'!$B$6:$B$149,A5,'Scope Checklist'!$E$6:$E$149,"Not Needed") -> 0 | G5: =SUMIF('Scope Checklist'!$B$6:$B$149,A5,'Scope Checklist'!$L$6:$L$149) -> 0 | H5: =SUMIF('Scope Checklist'!$B$6:$B$149,A5,'Scope Checklist'!$M$6:$M$149) -> 0
A6: Exterior | B6: =COUNTIF('Scope Checklist'!$B$6:$B$149,A6) -> 0 | C6: =COUNTIFS('Scope Checklist'!$B$6:$B$149,A6,'Scope Checklist'!$E$6:$E$149,"Pending") -> 0 | D6: =COUNTIFS('Scope Checklist'!$B$6:$B$149,A6,'Scope Checklist'!$E$6:$E$149,"In Progress") -> 0 | E6: =COUNTIFS('Scope Checklist'!$B$6:$B$149,A6,'Scope Checklist'!$E$6:$E$149,"Complete") -> 0 | F6: =COUNTIFS('Scope Checklist'!$B$6:$B$149,A6,'Scope Checklist'!$E$6:$E$149,"Not Needed") -> 0 | G6: =SUMIF('Scope Checklist'!$B$6:$B$149,A6,'Scope Checklist'!$L$6:$L$149) -> 0 | H6: =SUMIF('Scope Checklist'!$B$6:$B$149,A6,'Scope Checklist'!$M$6:$M$149) -> 0
A7: Interior - Demo/Structure | B7: =COUNTIF('Scope Checklist'!$B$6:$B$149,A7) -> 13 | C7: =COUNTIFS('Scope Checklist'!$B$6:$B$149,A7,'Scope Checklist'!$E$6:$E$149,"Pending") -> 10 | D7: =COUNTIFS('Scope Checklist'!$B$6:$B$149,A7,'Scope Checklist'!$E$6:$E$149,"In Progress") -> 0 | E7: =COUNTIFS('Scope Checklist'!$B$6:$B$149,A7,'Scope Checklist'!$E$6:$E$149,"Complete") -> 2 | F7: =COUNTIFS('Scope Checklist'!$B$6:$B$149,A7,'Scope Checklist'!$E$6:$E$149,"Not Needed") -> 1 | G7: =SUMIF('Scope Checklist'!$B$6:$B$149,A7,'Scope Checklist'!$L$6:$L$149) -> 0 | H7: =SUMIF('Scope Checklist'!$B$6:$B$149,A7,'Scope Checklist'!$M$6:$M$149) -> 0
A8: Interior - Electrical | B8: =COUNTIF('Scope Checklist'!$B$6:$B$149,A8) -> 11 | C8: =COUNTIFS('Scope Checklist'!$B$6:$B$149,A8,'Scope Checklist'!$E$6:$E$149,"Pending") -> 8 | D8: =COUNTIFS('Scope Checklist'!$B$6:$B$149,A8,'Scope Checklist'!$E$6:$E$149,"In Progress") -> 3 | E8: =COUNTIFS('Scope Checklist'!$B$6:$B$149,A8,'Scope Checklist'!$E$6:$E$149,"Complete") -> 0 | F8: =COUNTIFS('Scope Checklist'!$B$6:$B$149,A8,'Scope Checklist'!$E$6:$E$149,"Not Needed") -> 0 | G8: =SUMIF('Scope Checklist'!$B$6:$B$149,A8,'Scope Checklist'!$L$6:$L$149) -> 14000 | H8: =SUMIF('Scope Checklist'!$B$6:$B$149,A8,'Scope Checklist'!$M$6:$M$149) -> 7000
A9: Interior - Plumbing | B9: =COUNTIF('Scope Checklist'!$B$6:$B$149,A9) -> 7 | C9: =COUNTIFS('Scope Checklist'!$B$6:$B$149,A9,'Scope Checklist'!$E$6:$E$149,"Pending") -> 5 | D9: =COUNTIFS('Scope Checklist'!$B$6:$B$149,A9,'Scope Checklist'!$E$6:$E$149,"In Progress") -> 0 | E9: =COUNTIFS('Scope Checklist'!$B$6:$B$149,A9,'Scope Checklist'!$E$6:$E$149,"Complete") -> 1 | F9: =COUNTIFS('Scope Checklist'!$B$6:$B$149,A9,'Scope Checklist'!$E$6:$E$149,"Not Needed") -> 1 | G9: =SUMIF('Scope Checklist'!$B$6:$B$149,A9,'Scope Checklist'!$L$6:$L$149) -> 0 | H9: =SUMIF('Scope Checklist'!$B$6:$B$149,A9,'Scope Checklist'!$M$6:$M$149) -> 1500
A10: Interior - HVAC | B10: =COUNTIF('Scope Checklist'!$B$6:$B$149,A10) -> 8 | C10: =COUNTIFS('Scope Checklist'!$B$6:$B$149,A10,'Scope Checklist'!$E$6:$E$149,"Pending") -> 7 | D10: =COUNTIFS('Scope Checklist'!$B$6:$B$149,A10,'Scope Checklist'!$E$6:$E$149,"In Progress") -> 0 | E10: =COUNTIFS('Scope Checklist'!$B$6:$B$149,A10,'Scope Checklist'!$E$6:$E$149,"Complete") -> 0 | F10: =COUNTIFS('Scope Checklist'!$B$6:$B$149,A10,'Scope Checklist'!$E$6:$E$149,"Not Needed") -> 1 | G10: =SUMIF('Scope Checklist'!$B$6:$B$149,A10,'Scope Checklist'!$L$6:$L$149) -> 2100 | H10: =SUMIF('Scope Checklist'!$B$6:$B$149,A10,'Scope Checklist'!$M$6:$M$149) -> 2000
A11: Kitchen | B11: =COUNTIF('Scope Checklist'!$B$6:$B$149,A11) -> 9 | C11: =COUNTIFS('Scope Checklist'!$B$6:$B$149,A11,'Scope Checklist'!$E$6:$E$149,"Pending") -> 7 | D11: =COUNTIFS('Scope Checklist'!$B$6:$B$149,A11,'Scope Checklist'!$E$6:$E$149,"In Progress") -> 1 | E11: =COUNTIFS('Scope Checklist'!$B$6:$B$149,A11,'Scope Checklist'!$E$6:$E$149,"Complete") -> 0 | F11: =COUNTIFS('Scope Checklist'!$B$6:$B$149,A11,'Scope Checklist'!$E$6:$E$149,"Not Needed") -> 1 | G11: =SUMIF('Scope Checklist'!$B$6:$B$149,A11,'Scope Checklist'!$L$6:$L$149) -> 36775 | H11: =SUMIF('Scope Checklist'!$B$6:$B$149,A11,'Scope Checklist'!$M$6:$M$149) -> 18475
A12: Bath - Master | B12: =COUNTIF('Scope Checklist'!$B$6:$B$149,A12) -> 19 | C12: =COUNTIFS('Scope Checklist'!$B$6:$B$149,A12,'Scope Checklist'!$E$6:$E$149,"Pending") -> 19 | D12: =COUNTIFS('Scope Checklist'!$B$6:$B$149,A12,'Scope Checklist'!$E$6:$E$149,"In Progress") -> 0 | E12: =COUNTIFS('Scope Checklist'!$B$6:$B$149,A12,'Scope Checklist'!$E$6:$E$149,"Complete") -> 0 | F12: =COUNTIFS('Scope Checklist'!$B$6:$B$149,A12,'Scope Checklist'!$E$6:$E$149,"Not Needed") -> 0 | G12: =SUMIF('Scope Checklist'!$B$6:$B$149,A12,'Scope Checklist'!$L$6:$L$149) -> 3000 | H12: =SUMIF('Scope Checklist'!$B$6:$B$149,A12,'Scope Checklist'!$M$6:$M$149) -> 6500
A13: Bath - Secondary | B13: =COUNTIF('Scope Checklist'!$B$6:$B$149,A13) -> 14 | C13: =COUNTIFS('Scope Checklist'!$B$6:$B$149,A13,'Scope Checklist'!$E$6:$E$149,"Pending") -> 14 | D13: =COUNTIFS('Scope Checklist'!$B$6:$B$149,A13,'Scope Checklist'!$E$6:$E$149,"In Progress") -> 0 | E13: =COUNTIFS('Scope Checklist'!$B$6:$B$149,A13,'Scope Checklist'!$E$6:$E$149,"Complete") -> 0 | F13: =COUNTIFS('Scope Checklist'!$B$6:$B$149,A13,'Scope Checklist'!$E$6:$E$149,"Not Needed") -> 0 | G13: =SUMIF('Scope Checklist'!$B$6:$B$149,A13,'Scope Checklist'!$L$6:$L$149) -> 0 | H13: =SUMIF('Scope Checklist'!$B$6:$B$149,A13,'Scope Checklist'!$M$6:$M$149) -> 0
A14: Interior - Finishes | B14: =COUNTIF('Scope Checklist'!$B$6:$B$149,A14) -> 15 | C14: =COUNTIFS('Scope Checklist'!$B$6:$B$149,A14,'Scope Checklist'!$E$6:$E$149,"Pending") -> 15 | D14: =COUNTIFS('Scope Checklist'!$B$6:$B$149,A14,'Scope Checklist'!$E$6:$E$149,"In Progress") -> 0 | E14: =COUNTIFS('Scope Checklist'!$B$6:$B$149,A14,'Scope Checklist'!$E$6:$E$149,"Complete") -> 0 | F14: =COUNTIFS('Scope Checklist'!$B$6:$B$149,A14,'Scope Checklist'!$E$6:$E$149,"Not Needed") -> 0 | G14: =SUMIF('Scope Checklist'!$B$6:$B$149,A14,'Scope Checklist'!$L$6:$L$149) -> 0 | H14: =SUMIF('Scope Checklist'!$B$6:$B$149,A14,'Scope Checklist'!$M$6:$M$149) -> 0
A15: Closeout | B15: =COUNTIF('Scope Checklist'!$B$6:$B$149,A15) -> 6 | C15: =COUNTIFS('Scope Checklist'!$B$6:$B$149,A15,'Scope Checklist'!$E$6:$E$149,"Pending") -> 6 | D15: =COUNTIFS('Scope Checklist'!$B$6:$B$149,A15,'Scope Checklist'!$E$6:$E$149,"In Progress") -> 0 | E15: =COUNTIFS('Scope Checklist'!$B$6:$B$149,A15,'Scope Checklist'!$E$6:$E$149,"Complete") -> 0 | F15: =COUNTIFS('Scope Checklist'!$B$6:$B$149,A15,'Scope Checklist'!$E$6:$E$149,"Not Needed") -> 0 | G15: =SUMIF('Scope Checklist'!$B$6:$B$149,A15,'Scope Checklist'!$L$6:$L$149) -> 0 | H15: =SUMIF('Scope Checklist'!$B$6:$B$149,A15,'Scope Checklist'!$M$6:$M$149) -> 0
A16: TOTAL | B16: =SUM(B5:B15) -> 127 | C16: =SUM(C5:C15) -> 113 | D16: =SUM(D5:D15) -> 6 | E16: =SUM(E5:E15) -> 4 | F16: =SUM(F5:F15) -> 4 | G16: =SUM(G5:G15) -> 55875 | H16: =SUM(H5:H15) -> 35475
